bontakte/__init__.py
bontakte/api.py
bontakte/client.py
bontakte/events.py
bontakte/handlers.py
bontakte/types.py
bontakte/utils.py
bontakte-0.1.0.dist-info/licenses/LICENSE
bontakte-0.1.0.dist-info/METADATA
bontakte-0.1.0.dist-info/WHEEL
bontakte-0.1.0.dist-info/top_level.txt
bontakte-0.1.0.dist-info/RECORD
